[
]
[
	{"text":"\n        func As(err error, target interface{}) bool"},
	{"text":"\n        func Is(err, target error) bool"},
	{"text":"\n        func New(text string) error"},
	{"text":"\n        func Unwrap(err error) error"},
]
[
	{"text":"\n        func As(err error, target interface{}) bool"},
	{"text":"\n        func Is(err, target error) bool"},
	{"text":"\n        func New(text string) error"},
	{"text":"\n        func Unwrap(err error) error"},
]
[
	{"text":"\n        func As(err error, target interface{}) bool"},
	{"text":"\n        func Is(err, target error) bool"},
	{"text":"\n        func New(text string) error"},
	{"text":"\n        func Unwrap(err error) error"},
]
[
	{"text":"\n        func As(err error, target interface{}) bool"},
	{"text":"\n        func Is(err, target error) bool"},
	{"text":"\n        func New(text string) error"},
	{"text":"\n        func Unwrap(err error) error"},
]
